{
  "id": "001D9306",
  "countryCode": "CA",
  "locale": "fr-CA",
  "name": "Shell Gadus S3 V460D 1",
  "description": "Premium Multipurpose Heavy Duty Grease with Solids",
  "family": "Gadus",
  "parentCategory": "",
  "category": "Graisses EP à base d’huile minérale",
  "applicationKeys": [
    "ep",
    "extreme pressure",
    "gearbox",
    "heavy duty",
    "heavy load",
    "high temperature",
    "industrial",
    "lithium",
    "lithium complex",
    "mining",
    "moly",
    "multipurpose",
    "plain bearings",
    "premium",
    "roller bearings",
    "shock load",
    "slow",
    "slow moving",
    "solid lubricant",
    "steel",
    "water resistance"
  ],
  "position": "Premium",
  "viscosityGrade": "1",
  "viscosityType": "NLGI",
  "fluidType": "Mineral",
  "fluidSubType": "Mineral",
  "globalDocs": [
    {
      "href": "https://www.shell-livedocs.com/data/published/en/f176cb48-f0c8-48e3-ba2b-c23c47df9fa2.pdf",
      "type": "GTDS",
      "name": "Gadus S3 V460D 1 EN TDG V2.4 26-Dec-2019",
      "language": "EN"
    }
  ],
  "localDocs": [
    {
      "href": "https://www.shell-livedocs.com/data/published/en-CA/66ddac0c-666f-4329-bbce-a11ed0754912.pdf",
      "type": "LTDS",
      "name": "Gadus S3 V460D 1 Canada EN TDG V2.4 30-Dec-2019",
      "language": "EN"
    },
    {
      "href": "www.epc.shell.com/docs/GSAP_msds_02520718.PDF",
      "type": "LMSDS",
      "name": "Gadus S3 V460D 1 Canada FR 140006579500 EHS V4.1 01-FEB-2023",
      "language": "FR"
    },
    {
      "href": "www.epc.shell.com/docs/GSAP_msds_02520717.PDF",
      "type": "LMSDS",
      "name": "Gadus S3 V460D 1 Canada EN 140006579500 EHS V4.1 01-FEB-2023",
      "language": "EN"
    },
    {
      "href": "https://www.shell-livedocs.com/data/published/fr-CA/95f5f5ed-e39e-4088-a131-804b1cc0e1a1.pdf",
      "type": "LTDS",
      "name": "Gadus S3 V460D 1 Canada FR TDG V2.4 17-Aug-2020",
      "language": "FR"
    }
  ],
  "packs": [
    {
      "code": "001D9306_002XL3_A1WJ",
      "name": "",
      "size": "0.4",
      "uom": "kg",
      "pack": "Cartouche ",
      "materialCode": "550027649",
      "margin": "2.77352561782568",
      "packShot": ""
    },
    {
      "code": "001D9306_002WWP_A1WJ",
      "name": "",
      "size": "208",
      "uom": "L",
      "pack": "Baril",
      "materialCode": "550026860",
      "margin": "1.35085183602792",
      "packShot": ""
    },
    {
      "code": "001D9306_002VKN_A1WJ",
      "name": "",
      "size": "50",
      "uom": "kg",
      "pack": "Tonneau",
      "materialCode": "550026861",
      "margin": "1.36468666362762",
      "packShot": ""
    }
  ],
  "globalSpecs": [],
  "localSpecs": [],
  "marketing": "\nLes graisses Shell Gadus S3 V460D sont des graisses hautes performances hautes températures destinées aux grands roulements à déplacement lent soumis à des chocs. Ils sont à base d'huile minérale à indice de viscosité élevé et d'un épaississant au savon complexe de lithium. En plus de contenir les derniers additifs pour assurer d'excellentes performances à haute température, anti-corrosion et anti-oxydation, ils contiennent également des solides pour garantir que la graisse peut supporter des chocs.",
  "physicalCharacteristics": [],
  "active": true,
  "carbonNeutral": null,
  "packShot": null,
  "valueRecord": [],
  "commerce": null
}