{
  "id": "001D5430",
  "countryCode": "US",
  "locale": "en-US",
  "name": "Shell Rotella T1 50",
  "description": "High Quality Straight Grade Heavy Duty Diesel Engine Oil ",
  "family": "Rotella",
  "parentCategory": null,
  "category": "Engine Oils - Heavy Duty",
  "applicationKeys": [
    "axle",
    "final drive",
    "gearbox",
    "hydraulic system",
    "industrial",
    "manual sequential",
    "marine",
    "marine reversing gears",
    "mobile",
    "off highway",
    "pump gear",
    "reduction gears",
    "transmissions"
  ],
  "position": "Entry",
  "viscosityGrade": "50",
  "viscosityType": "SAE",
  "fluidType": "Mineral",
  "fluidSubType": "Mineral",
  "globalDocs": [
    {
      "href": "www.epc.shell.com/docs/GPCDOC_GTDS_Shell_Rotella_T1_50_(CF_CF-2)_(en)_TDS.pdf",
      "type": "GTDS",
      "name": "Rotella T1 50 (CF/CF-2) English",
      "language": "EN"
    }
  ],
  "localDocs": [
    {
      "href": "www.epc.shell.com/docs/GSAP_msds_02563901.PDF",
      "type": "LMSDS",
      "name": "Rotella T1 50 (CF/CF-2) United States EN 140002686046 EHS V1.5 06-APR-2023",
      "language": "EN"
    },
    {
      "href": "http://www.shell-livedocs.com/data/published/en-US/2fa01694-7d3a-4859-95af-b6534c385f77.pdf",
      "type": "LTDS",
      "name": "Rotella T1 50 (CF/CF-2) United States EN TDG V2.2 06-May-2016",
      "language": "EN"
    }
  ],
  "packs": [],
  "globalSpecs": [
    {
      "name": "API CF",
      "organisation": "API",
      "spec": "CF"
    },
    {
      "name": "API CF-2",
      "organisation": "API",
      "spec": "CF-2"
    }
  ],
  "localSpecs": [],
  "marketing": "Shell Rotella^®^ T1 Energized Protection™ oils use well-proven performance additives to fight engine wear and prevent deposits, providing reliable lubrication and consistent performance. Suitable for day to day use in turbo and non-turbocharged older engines.",
  "physicalCharacteristics": [],
  "active": false,
  "carbonNeutral": null,
  "packShot": null,
  "valueRecord": [],
  "commerce": null
}