{
  "id": "001I3579",
  "countryCode": "US",
  "locale": "en-US",
  "name": "Advance 4T AX5 20W-50 (SL/MA2)",
  "description": "4 stroke motorcycle engine oil",
  "family": "Advance",
  "parentCategory": null,
  "category": "Engine Oils - Motorcycle",
  "applicationKeys": [
    "four stroke",
    "motorbikes",
    "motorcycles"
  ],
  "position": "Mainstream",
  "viscosityGrade": "20W-50",
  "viscosityType": "SAE",
  "fluidType": "Mineral",
  "fluidSubType": "Mineral",
  "globalDocs": [
    {
      "href": "https://www.shell-livedocs.com/data/published/en/353b0111-78ba-4371-9734-2f51d2170819.pdf",
      "type": "GTDS",
      "name": "Advance 4T AX5 20W-50 (SL/MA2) EN TDG V1.0 03-Jan-2020",
      "language": "EN"
    }
  ],
  "localDocs": [
    {
      "href": "www.epc.shell.com/docs/GSAP_msds_02563920.PDF",
      "type": "LMSDS",
      "name": "Advance 4T AX5 20W-50 (SL/MA2) United States EN 140002686046 EHS V1.2 28-APR-2021",
      "language": "EN"
    }
  ],
  "packs": [],
  "globalSpecs": [
    {
      "name": "JASO MA2",
      "organisation": "JASO",
      "spec": "MA2"
    },
    {
      "name": "API SL",
      "organisation": "API",
      "spec": "SL"
    }
  ],
  "localSpecs": [],
  "marketing": "Shell Advance 4T AX5 four-stroke motorcycle engine oil meets the requirements of most motorcycle manufacturers.",
  "physicalCharacteristics": [],
  "active": false,
  "carbonNeutral": null,
  "packShot": null,
  "valueRecord": [],
  "commerce": null
}