{
  "id": "001J1458",
  "countryCode": "US",
  "locale": "en-US",
  "name": "ACCO 100",
  "description": "Rotary/Reciprocating Air Compressor Oil",
  "family": "Generic Branded Product",
  "parentCategory": null,
  "category": "Compressor and Vacuum Pump",
  "applicationKeys": [
    ""
  ],
  "position": "OEM Speciality",
  "viscosityGrade": "100",
  "viscosityType": "ISO",
  "fluidType": null,
  "fluidSubType": "-",
  "globalDocs": [
    {
      "href": "https://www.shell-livedocs.com/data/published/en/0f650fa7-16d8-40f7-be6c-3419ae8d0429.pdf",
      "type": "GTDS",
      "name": "Shell ACCO 100 EN TDG V1.0 13-Nov-2020",
      "language": "EN"
    }
  ],
  "localDocs": [
    {
      "href": "www.epc.shell.com/docs/GSAP_msds_02563755.PDF",
      "type": "LMSDS",
      "name": "Shell ACCO 100 United States EN 140002686046 EHS V1.0 08-DEC-2020",
      "language": "EN"
    }
  ],
  "packs": [],
  "globalSpecs": [],
  "localSpecs": [],
  "marketing": "",
  "physicalCharacteristics": [],
  "active": false,
  "carbonNeutral": null,
  "packShot": null,
  "valueRecord": [],
  "commerce": null
}