{
  "id": "001J1862",
  "countryCode": "US",
  "locale": "en-US",
  "name": "Shell Spirax S3 GD 80W",
  "description": "High Performance Manual Transmission and Gear Oil for Mercedes, Eaton and Isuzu.",
  "family": "Spirax",
  "parentCategory": null,
  "category": "Manual Transmission and Gear Oils",
  "applicationKeys": [
    ""
  ],
  "position": "Mainstream",
  "viscosityGrade": "80W",
  "viscosityType": "SAE",
  "fluidType": "Mineral",
  "fluidSubType": "Mineral",
  "globalDocs": [
    {
      "href": "https://www.shell-livedocs.com/data/published/en/7aaa6f9a-9331-48c9-8499-8c31a09c2c38.pdf",
      "type": "GTDS",
      "name": "Spirax S3 GD 80W EN TDG V1.0 25-Nov-2020",
      "language": "EN"
    }
  ],
  "localDocs": [
    {
      "href": "www.epc.shell.com/docs/GSAP_msds_02562999.PDF",
      "type": "LMSDS",
      "name": "Spirax S3 GD 80W United States EN 140002686046 EHS V1.1 17-FEB-2023",
      "language": "EN"
    }
  ],
  "packs": [],
  "globalSpecs": [],
  "localSpecs": [],
  "marketing": "Shell Spirax S3 GD 80W is a long-life gearbox oil designed to give new benefits based on improved levels of performance to meet the future requirements of gearboxes. Specially optimised mineral base oils and new additive technology improve lubrication of the drive train and potentially extend oil drain intervals. High performance manual transmission and gear oil for Mercedes, Eaton and Isuzu.",
  "physicalCharacteristics": [],
  "active": false,
  "carbonNeutral": null,
  "packShot": null,
  "valueRecord": [],
  "commerce": null
}