{
  "id": "163C0096",
  "countryCode": "US",
  "locale": "en-US",
  "name": "Shell SC 352",
  "description": "2 stroke engine oil",
  "family": "Chainsaw",
  "parentCategory": null,
  "category": "Engine Oils - Other",
  "applicationKeys": [
    ""
  ],
  "position": "Entry",
  "viscosityGrade": "Other (unspecified)",
  "viscosityType": "-",
  "fluidType": "Mineral",
  "fluidSubType": "Mineral",
  "globalDocs": [],
  "localDocs": [],
  "packs": [],
  "globalSpecs": [],
  "localSpecs": [],
  "marketing": "Properties include high thermal stability, less piston ring sticking and less skirt deposits, low combustion chamber and exhaust deposits with reduced spark-plug fouling and excellent anti-rust properties.",
  "physicalCharacteristics": [],
  "active": false,
  "carbonNeutral": null,
  "packShot": null,
  "valueRecord": [],
  "commerce": null
}