{
  "id": "001D8274",
  "countryCode": "SG",
  "locale": "en-SG",
  "name": "Shell Spirax S2 A 140",
  "description": "High quality, GL-5 axle oil",
  "family": "Spirax",
  "parentCategory": null,
  "category": "Manual Transmission and Gear Oils",
  "applicationKeys": [
    "automatic",
    "axle",
    "differential",
    "final drive",
    "gearbox",
    "hydraulic system",
    "industrial",
    "manual",
    "manual sequential",
    "off highway",
    "reduction gears",
    "screw pump",
    "synchronised",
    "tandem drive",
    "transmissions"
  ],
  "position": "Entry",
  "viscosityGrade": "140",
  "viscosityType": "SAE",
  "fluidType": "Mineral",
  "fluidSubType": "Mineral",
  "globalDocs": [
    {
      "href": "www.epc.shell.com/docs/GPCDOC_GTDS_Shell_Spirax_S2_A_140_(en)_TDS.pdf",
      "type": "GTDS",
      "name": "Spirax S2 A 140 English",
      "language": "EN"
    }
  ],
  "localDocs": [
    {
      "href": "www.epc.shell.com/docs/GSAP_msds_02580322.PDF",
      "type": "LMSDS",
      "name": "Spirax S2 A 140 Singapore English",
      "language": "EN"
    }
  ],
  "packs": [
    {
      "code": "001D8274_002VSH_A227",
      "name": "Drum 209 L T/H RYtop (1)",
      "size": "209",
      "uom": "L",
      "pack": "Drum",
      "materialCode": "550024931",
      "margin": "Not found",
      "packShot": ""
    },
    {
      "code": "001D8274_001176_A03Q",
      "name": "No Packaging (BULK)",
      "size": "BULK",
      "uom": "",
      "pack": "No packaging",
      "materialCode": "500005728",
      "margin": "Not found",
      "packShot": ""
    }
  ],
  "globalSpecs": [
    {
      "name": "API GL-5",
      "organisation": "API",
      "spec": "GL-5"
    }
  ],
  "localSpecs": [],
  "marketing": "Shell Spirax S2 A 140 is blended for use in a wide variety of automotive axle units subjected to heavy duty conditions.",
  "physicalCharacteristics": [
    {
      "property": "SAE Viscosity Grade",
      "method": "SAE J 306",
      "uom": "NULL",
      "units": "NULL",
      "value": "140"
    },
    {
      "property": "Kinematic Viscosity",
      "method": "ISO 3104",
      "uom": "@40°C",
      "units": "mm²/s",
      "value": "340"
    },
    {
      "property": "Kinematic Viscosity",
      "method": "ISO 3104",
      "uom": "@100°C",
      "units": "mm²/s",
      "value": "25.1"
    },
    {
      "property": "Viscosity Index",
      "method": "ISO 2909",
      "uom": "NULL",
      "units": "NULL",
      "value": "96"
    },
    {
      "property": "Density",
      "method": "ISO 12185",
      "uom": "@15°C",
      "units": "kg/m³",
      "value": "918"
    },
    {
      "property": "Flash Point (COC)",
      "method": "ISO 2592",
      "uom": "NULL",
      "units": "°C",
      "value": "199"
    },
    {
      "property": "Pour Point",
      "method": "ISO 3016",
      "uom": "NULL",
      "units": "°C",
      "value": "-9"
    }
  ],
  "active": true,
  "carbonNeutral": null,
  "packShot": "https://s3.amazonaws.com/oats.packshots/shell_lubematch/shell/B2B-montage.png",
  "valueRecord": [],
  "commerce": null
}