{
  "id": "001F3415",
  "countryCode": "SG",
  "locale": "en-SG",
  "name": "Ondina X 432",
  "description": "High Quality Medicinal White Oil",
  "family": "Ondina",
  "parentCategory": null,
  "category": "Medicinal White Oils",
  "applicationKeys": [
    ""
  ],
  "position": "OEM Speciality",
  "viscosityGrade": "Other (unspecified)",
  "viscosityType": "-",
  "fluidType": "Semi-synthetic",
  "fluidSubType": "Blend",
  "globalDocs": [
    {
      "href": "www.epc.shell.com/docs/GPCDOC_GTDS_Shell_Ondina_X_432_(en)_TDS.pdf",
      "type": "GTDS",
      "name": "Shell Ondina X 432 English",
      "language": "EN"
    }
  ],
  "localDocs": [
    {
      "href": "www.epc.shell.com/docs/GSAP_msds_02580489.PDF",
      "type": "LMSDS",
      "name": "Ondina X 432 Singapore English",
      "language": "EN"
    }
  ],
  "packs": [
    {
      "code": "001F3415_002VSH_A1P5",
      "name": "Drum 209 L T/H RYtop (1)",
      "size": "209",
      "uom": "L",
      "pack": "Drum",
      "materialCode": "550041891",
      "margin": "Not found",
      "packShot": ""
    }
  ],
  "globalSpecs": [],
  "localSpecs": [],
  "marketing": "Shell Ondina X 432 is a highly refined, non-stabilised, aromatic-free mainly iso-paraffinic white mineral oil complying with the stringent pharmacopoeia purity requirements.",
  "physicalCharacteristics": [],
  "active": true,
  "carbonNeutral": null,
  "packShot": null,
  "valueRecord": [],
  "commerce": null
}