{
  "id": "001D8307",
  "countryCode": "DE",
  "locale": "de-DE",
  "name": "Shell Spirax S6 ATF ZM",
  "description": "Premium Heavy Duty Transmission Oil for ZF Long Drain",
  "family": "Spirax",
  "parentCategory": "Transmission fluids",
  "category": "ATF - Automatic Transmission Fluids",
  "applicationKeys": [
    "atf",
    "automatic",
    "automatic transmissions",
    "buses",
    "disc",
    "extended drain",
    "extended life",
    "gearbox",
    "heavy duty",
    "heavy duty atf",
    "heavy truck",
    "hydraulic system",
    "industrial",
    "low temperature",
    "manual",
    "manual sequential",
    "pump gear",
    "synchronised",
    "transmissions",
    "trucks",
    "wet brake",
    "zf ecomat"
  ],
  "position": "Premium",
  "viscosityGrade": "Other (unspecified)",
  "viscosityType": "-",
  "fluidType": "Synthetic",
  "fluidSubType": "Synthetic",
  "globalDocs": [
    {
      "href": "https://www.shell-livedocs.com/data/published/en/7262879e-2382-4618-8fa3-27b484daf46e.pdf",
      "type": "GTDS",
      "name": "Spirax S6 ATF ZM EN TDG V2.4 20-Sep-2019",
      "language": "EN"
    }
  ],
  "localDocs": [
    {
      "href": "www.epc.shell.com/docs/GSAP_msds_02578301.PDF",
      "type": "LMSDS",
      "name": "Spirax S6 ATF ZM Germany EN 140001492039 EHS V4.1 23-MAY-2023",
      "language": "EN"
    },
    {
      "href": "www.epc.shell.com/docs/GSAP_msds_02578300.PDF",
      "type": "LMSDS",
      "name": "Spirax S6 ATF ZM Germany DE 140001492039 EHS V4.1 23-MAY-2023",
      "language": "DE"
    },
    {
      "href": "https://www.shell-livedocs.com/data/published/de/5cd83656-f636-4b9f-b5b3-4d3e2791eec6.pdf",
      "type": "LTDS",
      "name": "Spirax S6 ATF ZM Germany DE TDG V2.4 20-Nov-2019",
      "language": "DE"
    }
  ],
  "packs": [
    {
      "code": "001D8307_001176_SBLK",
      "name": "No Packaging (Bulkware)",
      "size": "BULK",
      "uom": "",
      "pack": "Keine Verpackung",
      "materialCode": "500006351",
      "margin": "2.04983041526674",
      "packShot": ""
    }
  ],
  "globalSpecs": [
    {
      "name": "ZF TE-ML 4D",
      "organisation": "ZF",
      "spec": "TE-ML 4D"
    },
    {
      "name": "ZF TE-ML 20F",
      "organisation": "ZF",
      "spec": "TE-ML 20F"
    },
    {
      "name": "MAN 339 Type Z13",
      "organisation": "MAN",
      "spec": "339 Type Z13"
    },
    {
      "name": "ZF TE-ML 16Q",
      "organisation": "ZF",
      "spec": "TE-ML 16Q"
    },
    {
      "name": "ZF TE-ML 14E",
      "organisation": "ZF",
      "spec": "TE-ML 14E"
    },
    {
      "name": "MAN 339 Type Z4",
      "organisation": "MAN",
      "spec": "339 Type Z4"
    },
    {
      "name": "ZF TE-ML 16N",
      "organisation": "ZF",
      "spec": "TE-ML 16N"
    }
  ],
  "localSpecs": [],
  "marketing": "Shell Spirax S6 ATF ZM ist ein teilsynthetisches Hochleistungs-Automatikgetriebeöl mit Premiumqualität, welches in Zusammenarbeit mit ZF als Getriebeöl für die neueste Generation von ZF-Ecomat- und ZF-Ecolife-Getrieben entwickelt wurde. Es ist ein extrem leistungsstarkes Automatikgetriebeöl, welches für verlängerte Ölwechselintervalle freigegeben ist und auch unter schweren Betriebsbedingungen stabil bleibt.",
  "physicalCharacteristics": [
    {
      "property": "Kinematische Viskosität",
      "method": "ISO 3104",
      "uom": "@40 °C",
      "units": "mm²/s",
      "value": "61,8"
    },
    {
      "property": "Kinematische Viskosität",
      "method": "ISO 3104",
      "uom": "@100 °C",
      "units": "mm²/s",
      "value": "10,2"
    },
    {
      "property": "Viskositätsindex",
      "method": "ISO 2909",
      "uom": "",
      "units": "",
      "value": "153"
    },
    {
      "property": "Dichte",
      "method": "ISO 12185",
      "uom": "@15 °C",
      "units": "kg/m³",
      "value": "843"
    },
    {
      "property": "Flammpunkt (COC)",
      "method": "ISO 2592",
      "uom": "",
      "units": "°C",
      "value": "240"
    },
    {
      "property": "Pourpoint",
      "method": "ISO 3016",
      "uom": "",
      "units": "°C",
      "value": "–51"
    }
  ],
  "active": true,
  "carbonNeutral": null,
  "packShot": "https://s3.amazonaws.com/oats.packshots/shell_lubematch/shell/shell_spirax_s6_atf_zm_153.png",
  "valueRecord": [],
  "commerce": null
}