{
  "id": "001G1489",
  "countryCode": "TR",
  "locale": "tr-TR",
  "name": "Gadus S2 V160 0",
  "description": "High Performance Multipurpose Extreme Pressure Grease",
  "family": "Gadus",
  "parentCategory": "",
  "category": "Mineral oil based EP Greases",
  "applicationKeys": [
    "lithium"
  ],
  "position": "Mainstream",
  "viscosityGrade": "0",
  "viscosityType": "NLGI",
  "fluidType": "Mineral",
  "fluidSubType": "Mineral",
  "globalDocs": [
    {
      "href": "https://www.shell-livedocs.com/data/published/en/069968c8-394d-47b7-a4b7-3946e3558f5f.pdf",
      "type": "GTDS",
      "name": "Gadus S2 V160 0 EN TDG V1.4 21-Sep-2021",
      "language": "EN"
    }
  ],
  "localDocs": [
    {
      "href": "www.epc.shell.com/docs/GSAP_msds_02311249.PDF",
      "type": "LMSDS",
      "name": "Gadus S2 V160 0 Turkey TR 140003791542 EHS V1.6 06-MAY-2021",
      "language": "TR"
    },
    {
      "href": "www.epc.shell.com/docs/GSAP_msds_02311251.PDF",
      "type": "LMSDS",
      "name": "Gadus S2 V160 0 Turkey EN 140003791542 EHS V1.6 06-MAY-2021",
      "language": "EN"
    },
    {
      "href": "https://www.shell-livedocs.com/data/published/tr/45e019a3-12ed-4d67-865e-55db95103bf0.pdf",
      "type": "LTDS",
      "name": "Gadus S2 V160 0 Turkey TR TDG V1.4 29-Sep-2021",
      "language": "TR"
    }
  ],
  "packs": [
    {
      "code": "001G1489_002VH7_A246",
      "name": "Fıçı 180 kg O/H RYTop (1)",
      "size": "180",
      "uom": "kilogram",
      "pack": "Fıçı",
      "materialCode": "550046840",
      "margin": "Not found",
      "packShot": ""
    }
  ],
  "globalSpecs": [],
  "localSpecs": [],
  "marketing": "Shell Gadus S2 V160 0, özellikle mermer ocaklarında bulunan kesme makinalarında kullanılmak üzere geliştirlmiştir. Ayrıca endüstriyel uygulamalarda da kullanıma uygun çok amaçlı bir grestir.",
  "physicalCharacteristics": [],
  "active": true,
  "carbonNeutral": null,
  "packShot": null,
  "valueRecord": [],
  "commerce": null
}